CHANGES.txt
LICENSE.txt
MANIFEST.in
README.txt
setup.py
js/__init__.py
js.jquery_jstree.egg-info/PKG-INFO
js.jquery_jstree.egg-info/SOURCES.txt
js.jquery_jstree.egg-info/dependency_links.txt
js.jquery_jstree.egg-info/entry_points.txt
js.jquery_jstree.egg-info/namespace_packages.txt
js.jquery_jstree.egg-info/not-zip-safe
js.jquery_jstree.egg-info/requires.txt
js.jquery_jstree.egg-info/top_level.txt
js/jquery_jstree/__init__.py
js/jquery_jstree/test_jquery_jstree.txt
js/jquery_jstree/resources/README.txt
js/jquery_jstree/resources/jquery.jstree.js
js/jquery_jstree/resources/_lib/jquery.cookie.js
js/jquery_jstree/resources/_lib/jquery.hotkeys.js
js/jquery_jstree/resources/themes/apple/bg.jpg
js/jquery_jstree/resources/themes/apple/d.png
js/jquery_jstree/resources/themes/apple/dot_for_ie.gif
js/jquery_jstree/resources/themes/apple/style.css
js/jquery_jstree/resources/themes/apple/throbber.gif
js/jquery_jstree/resources/themes/classic/d.png
js/jquery_jstree/resources/themes/classic/dot_for_ie.gif
js/jquery_jstree/resources/themes/classic/style.css
js/jquery_jstree/resources/themes/classic/throbber.gif
js/jquery_jstree/resources/themes/default/d.gif
js/jquery_jstree/resources/themes/default/d.png
js/jquery_jstree/resources/themes/default/style.css
js/jquery_jstree/resources/themes/default/throbber.gif
js/jquery_jstree/resources/themes/default-rtl/d.gif
js/jquery_jstree/resources/themes/default-rtl/d.png
js/jquery_jstree/resources/themes/default-rtl/dots.gif
js/jquery_jstree/resources/themes/default-rtl/style.css
js/jquery_jstree/resources/themes/default-rtl/throbber.gif