Metadata-Version: 1.0
Name: js.jquery-jstree
Version: 1.0rc2
Summary: Fanstatic packaging of jQuery JsTree
Home-page: UNKNOWN
Author: Fanstatic Developers
Author-email: fanstatic@googlegroups.com
License: BSD
Platform: UNKNOWN
